LICENSE
MANIFEST.in
README.md
setup.cfg
setup.py
pylonctl/__init__.py
pylonctl/camera.py
pylonctl/cli.py
pylonctl.egg-info/PKG-INFO
pylonctl.egg-info/SOURCES.txt
pylonctl.egg-info/dependency_links.txt
pylonctl.egg-info/entry_points.txt
pylonctl.egg-info/requires.txt
pylonctl.egg-info/top_level.txt
pylonctl/gui/__init__.py
pylonctl/gui/main.py
pylonctl/gui/main.ui
pylonctl/gui/param.py