Metadata-Version: 2.1
Name: pylonctl
Version: 0.2.8
Summary: pylon control CLI
Home-page: https://github.com/tiagocoutinho/pylonctl
Author: Jose Tiago Macara Coutinho
Author-email: coutinhotiago@gmail.com
License: UNKNOWN
Keywords: pylon,CLI
Platform: UNKNOWN
Classifier: Development Status :: 2 - Pre-Alpha
Classifier: Intended Audience :: Developers
Classifier: Natural Language :: English
Classifier: Programming Language :: Python :: 3.7
Classifier: Programming Language :: Python :: 3.8
Classifier: License :: OSI Approved :: GNU General Public License v3 (GPLv3)
Requires-Python: >=3.7
